libmodbuspy/__init__.py
libmodbuspy/ascport.py
libmodbuspy/client.py
libmodbuspy/clientport.py
libmodbuspy/exceptions.py
libmodbuspy/mbconfig.py
libmodbuspy/mbglobal.py
libmodbuspy/mbinterface.py
libmodbuspy/mbobject.py
libmodbuspy/port.py
libmodbuspy/rtuport.py
libmodbuspy/serialport.py
libmodbuspy/serverport.py
libmodbuspy/serverresource.py
libmodbuspy/statuscode.py
libmodbuspy/tcpport.py
libmodbuspy/tcpserver.py
libmodbuspy/utils.py
libmodbuspy-0.4.0.dist-info/licenses/LICENSE
libmodbuspy-0.4.0.dist-info/METADATA
libmodbuspy-0.4.0.dist-info/WHEEL
libmodbuspy-0.4.0.dist-info/entry_points.txt
libmodbuspy-0.4.0.dist-info/top_level.txt
libmodbuspy-0.4.0.dist-info/RECORD
