Metadata-Version: 2.4
Name: libmodbuspy
Version: 0.4.0
Summary: A Python implementation of Modbus TCP, RTU, and ASCII protocols
Author-email: serhmarch <mrchsrg@gmail.com>
Maintainer-email: serhmarch <mrchsrg@gmail.com>
License: MIT
Project-URL: Homepage, https://github.com/serhmarch/libmodbuspy
Project-URL: Repository, https://github.com/serhmarch/libmodbuspy.git
Project-URL: Documentation, https://github.com/serhmarch/libmodbuspy/tree/main/doc
Project-URL: Bug Tracker, https://github.com/serhmarch/libmodbuspy/issues
Keywords: modbus,tcp,rtu,ascii,serial,industrial,automation,protocol,communication
Classifier: Development Status :: 4 - Beta
Classifier: Intended Audience :: Developers
Classifier: Intended Audience :: Manufacturing
Classifier: License :: OSI Approved :: MIT License
Classifier: Operating System :: OS Independent
Classifier: Programming Language :: Python :: 3
Classifier: Programming Language :: Python :: 3.7
Classifier: Programming Language :: Python :: 3.8
Classifier: Programming Language :: Python :: 3.9
Classifier: Programming Language :: Python :: 3.10
Classifier: Programming Language :: Python :: 3.11
Classifier: Programming Language :: Python :: 3.12
Classifier: Topic :: Communications
Classifier: Topic :: Scientific/Engineering
Classifier: Topic :: Software Development :: Libraries :: Python Modules
Classifier: Topic :: System :: Hardware
Classifier: Topic :: System :: Networking
Requires-Python: >=3.7
License-File: LICENSE
Requires-Dist: pyserial>=3.4
Provides-Extra: dev
Requires-Dist: pytest>=6.0; extra == "dev"
Requires-Dist: pytest-cov; extra == "dev"
Requires-Dist: black; extra == "dev"
Requires-Dist: flake8; extra == "dev"
Requires-Dist: mypy; extra == "dev"
Requires-Dist: sphinx; extra == "dev"
Requires-Dist: sphinx-rtd-theme; extra == "dev"
Provides-Extra: test
Requires-Dist: pytest>=6.0; extra == "test"
Requires-Dist: pytest-cov; extra == "test"
Provides-Extra: docs
Requires-Dist: sphinx; extra == "docs"
Requires-Dist: sphinx-rtd-theme; extra == "docs"
Requires-Dist: doxygen; extra == "docs"
Dynamic: license-file
